ragen/__init__.py
ragen/__version__.py
ragen/args.py
ragen/cmd.py
ragen/emb.py
ragen/file.py
ragen/llm.py
ragen-0.1.0.dist-info/LICENSE
ragen-0.1.0.dist-info/METADATA
ragen-0.1.0.dist-info/WHEEL
ragen-0.1.0.dist-info/entry_points.txt
ragen-0.1.0.dist-info/top_level.txt
ragen-0.1.0.dist-info/RECORD
